LOGS_solutions/__init__.py
LOGS_solutions/CreateExportEntities/__init__.py
LOGS_solutions/CreateExportEntities/Common/Exceptions.py
LOGS_solutions/CreateExportEntities/Common/__init__.py
LOGS_solutions/CreateExportEntities/CreateExportExperiments/ExperimentManager.py
LOGS_solutions/CreateExportEntities/CreateExportExperiments/__init__.py
LOGS_solutions/CreateExportEntities/CreateExportExperiments/main.py
LOGS_solutions/CreateExportEntities/CreateExportInstruments/InstrumentManager.py
LOGS_solutions/CreateExportEntities/CreateExportInstruments/__init__.py
LOGS_solutions/CreateExportEntities/CreateExportInstruments/main.py
LOGS_solutions/CreateExportEntities/CreateExportMethods/MethodManager.py
LOGS_solutions/CreateExportEntities/CreateExportMethods/__init__.py
LOGS_solutions/CreateExportEntities/CreateExportMethods/main.py
LOGS_solutions/CreateExportEntities/CreateExportPersons/PersonManager.py
LOGS_solutions/CreateExportEntities/CreateExportPersons/__init__.py
LOGS_solutions/CreateExportEntities/CreateExportPersons/main.py
LOGS_solutions/CreateExportEntities/CreateExportProjects/ProjectManager.py
LOGS_solutions/CreateExportEntities/CreateExportProjects/__init__.py
LOGS_solutions/CreateExportEntities/CreateExportProjects/main.py
LOGS_solutions/CreateExportEntities/CreateExportSamples/SampleManager.py
LOGS_solutions/CreateExportEntities/CreateExportSamples/__init__.py
LOGS_solutions/CreateExportEntities/CreateExportSamples/main.py
LOGS_solutions/DownloadDatasets/DatasetDownloader.py
LOGS_solutions/DownloadDatasets/DatasetHandler.py
LOGS_solutions/DownloadDatasets/FileHandler.py
LOGS_solutions/DownloadDatasets/ProgressBar.py
LOGS_solutions/DownloadDatasets/__init__.py
LOGS_solutions/DownloadDatasets/main.py
LOGS_solutions/GenerateStatistics/__init__.py
LOGS_solutions/GenerateStatistics/Common/CommonHandler.py
LOGS_solutions/GenerateStatistics/Common/DateHandler.py
LOGS_solutions/GenerateStatistics/Common/FileHandler.py
logs_py_solutions-0.3.4.dist-info/METADATA
logs_py_solutions-0.3.4.dist-info/WHEEL
logs_py_solutions-0.3.4.dist-info/top_level.txt
logs_py_solutions-0.3.4.dist-info/RECORD
