Metadata-Version: 2.4
Name: logs-py-solutions
Version: 0.3.4
Summary: Prebuild solution library for the logs-py package
Home-page: https://solutions.logs-python.com
Author: Bruker BioSpin GmbH & Co KG
Author-email: support@sciy.com
License: MIT
Classifier: Programming Language :: Python :: 3
Classifier: Operating System :: OS Independent
Classifier: Development Status :: 4 - Beta
Classifier: Intended Audience :: Science/Research
Requires-Python: >=3.8
Requires-Dist: logs-py>=3.0.14
Requires-Dist: ipykernel
Requires-Dist: jinja2
Requires-Dist: jupyter
Requires-Dist: matplotlib
Requires-Dist: pandas
Requires-Dist: pdf2image
Requires-Dist: pdfkit
Requires-Dist: plotly
Requires-Dist: PyPDF2
Requires-Dist: python-dateutil
Requires-Dist: qrcode[pil]
Requires-Dist: tqdm
Requires-Dist: wkhtmltopdf
Requires-Dist: openpyxl
Requires-Dist: colorama
Dynamic: author
Dynamic: author-email
Dynamic: classifier
Dynamic: description
Dynamic: description-content-type
Dynamic: home-page
Dynamic: license
Dynamic: requires-dist
Dynamic: requires-python
Dynamic: summary
